[
    {
        "x": "January 2025",
        "y": 1
    },
    {
        "x": "February 2025",
        "y": 179
    },
    {
        "x": "March 2025",
        "y": 102
    },
    {
        "x": "April 2025",
        "y": 0
    },
    {
        "x": "May 2025",
        "y": 0
    },
    {
        "x": "June 2025",
        "y": 0
    },
    {
        "x": "July 2025",
        "y": 0
    },
    {
        "x": "August 2025",
        "y": 0
    },
    {
        "x": "September 2025",
        "y": 0
    },
    {
        "x": "October 2025",
        "y": 0
    },
    {
        "x": "November 2025",
        "y": 0
    },
    {
        "x": "December 2025",
        "y": 0
    }
]